setup.py
proator/__init__.py
proator/function_prototype.py
proator.egg-info/PKG-INFO
proator.egg-info/SOURCES.txt
proator.egg-info/dependency_links.txt
proator.egg-info/not-zip-safe
proator.egg-info/top_level.txt