Metadata-Version: 1.0
Name: proator
Version: 1.1
Summary: Python function prototyping and call time check.
Home-page: https://github.com/mohit-thakur-721/proator
Author: Mohit Thakur
Author-email: mohit.thakur@nectechnologies.in
License: FREE
Platform: UNKNOWN
